gen_vhost/__init__.py
gen_vhost/py.typed
gen_vhost/conf/gen_vhost.cfg
gen_vhost/conf/gen_vhost.logo
gen_vhost/conf/gen_vhost_util.cfg
gen_vhost/conf/project.yaml
gen_vhost/conf/template/vhost_perl.template
gen_vhost/conf/template/vhost_php.template
gen_vhost/conf/template/vhost_python.template
gen_vhost/conf/template/vhost_ruby.template
gen_vhost/conf/template/vhost_static.template
gen_vhost/log/gen_vhost.log
gen_vhost/pro/__init__.py
gen_vhost/pro/read_template.py
gen_vhost/pro/write_template.py
usr/local/bin/gen_vhost_run.py
gen_vhost-1.1.4.dist-info/LICENSE
gen_vhost-1.1.4.dist-info/METADATA
gen_vhost-1.1.4.dist-info/WHEEL
gen_vhost-1.1.4.dist-info/top_level.txt
gen_vhost-1.1.4.dist-info/RECORD
