Metadata-Version: 2.1
Name: gen_vhost
Version: 1.1.4
Summary: VirtualHost generator
Home-page: https://vroncevic.github.io/gen_vhost/
Author: Vladimir Roncevic
Author-email: elektron.ronca@gmail.com
License: GPL 2017 - 2024 Free software to use and distributed it.
Keywords: VH,VirtualHost,project,Apache,Unix,Linux
Platform: POSIX
Classifier: Programming Language :: Python :: 3.10
Classifier: Programming Language :: Python :: 3.11
Classifier: License :: OSI Approved :: GNU Lesser General Public License v2 (LGPLv2)
Classifier: License :: OSI Approved :: GNU Lesser General Public License v2 or later (LGPLv2+)
Classifier: License :: OSI Approved :: GNU Lesser General Public License v3 (LGPLv3)
Classifier: License :: OSI Approved :: GNU Lesser General Public License v3 or later (LGPLv3+)
Classifier: License :: OSI Approved :: GNU Library or Lesser General Public License (LGPL)
Requires-Python: >=3.10
License-File: LICENSE
Requires-Dist: ats-utilities
